prompt_compression/__init__.py
prompt_compression/tools/__init__.py
prompt_compression/tools/prompt_compression_tool.py
prompt_compression/tools/utils.py
prompt_compression/yamls/prompt_compression_tool.yaml
tests/__init__.py
tests/test_prompt_compression_tool.py
prompt_compression-0.0.1.dist-info/METADATA
prompt_compression-0.0.1.dist-info/WHEEL
prompt_compression-0.0.1.dist-info/entry_points.txt
prompt_compression-0.0.1.dist-info/top_level.txt
prompt_compression-0.0.1.dist-info/RECORD
